itsmostdef/__init__.py
itsmostdef/main.py
itsmostdef-0.1.0.dist-info/METADATA
itsmostdef-0.1.0.dist-info/WHEEL
itsmostdef-0.1.0.dist-info/entry_points.txt
itsmostdef-0.1.0.dist-info/top_level.txt
itsmostdef-0.1.0.dist-info/RECORD
