Metadata-Version: 2.1
Name: itsmostdef
Version: 0.1.0
Summary: Whats in my fastq file?
Author: William Rosenbaum
Author-email: william.rosenbaum@gmail.com
License: MIT
Requires-Python: >=3.10
Requires-Dist: pandas
Requires-Dist: pyfastx
